ktz/__init__.py
ktz/collections.py
ktz/dataclasses.py
ktz/filesystem.py
ktz/functools.py
ktz/multiprocessing.py
ktz/py.typed
ktz/string.py
ktz-0.4.0.dist-info/LICENSE
ktz-0.4.0.dist-info/METADATA
ktz-0.4.0.dist-info/WHEEL
ktz-0.4.0.dist-info/RECORD
