Metadata-Version: 2.1
Name: ktz
Version: 0.4.0
Summary: Kantholtz' Python Toolbox
License: MIT
Author: Felix Hamann
Author-email: felix@hamann.xyz
Requires-Python: >=3.11,<4.0
Classifier: License :: OSI Approved :: MIT License
Classifier: Programming Language :: Python :: 3
Classifier: Programming Language :: Python :: 3.11
Classifier: Programming Language :: Python :: 3.12
Requires-Dist: PyYAML (>=6.0.1,<7.0.0)
Requires-Dist: notebook (>=7.2.0,<8.0.0)
